Workbook

Sheet Resumen
B2: ALFÉIZAR REFORMAS
B3: Estudio de Reformas de Vivienda en Valencia · Marta Alféizar
B5: PRESUPUESTO DE REFORMA INTEGRAL POR INDUSTRIALES
B7: Clientes: | C7: Lucía y Andrés García
B8: Vivienda: | C8: Piso de 60 m² construidos en Ruzafa (Valencia)
B9: Edificio: | C9: Año 1974 · Tercera planta con ascensor
B10: Fecha de oferta: | C10: 20/09/2026
B11: Validez: | C11: 30 días naturales
B12: Garantía: | C12: 2 años en mano de obra e instalaciones
B14: Capítulo (Industrial / Oficio) | C14: Resumen de Trabajos (Suministro y Colocación) | D14: Importe (sin IVA)
B15: 1. Derribos y gestión de residuos | C15: Demolición tabique cocina-salón, levantado pavimento 55 m², picado baño, desmontaje cocina y sanitarios, contenedor | D15: =Desglose!F11
B16: 2. Albañilería y revestimientos | C16: Cargadero metálico 4 m, alicatado azulejo blanco mate 30x60 P01 y suelo porcelánico gris perla 60x60 S02 | D16: =Desglose!F15
B17: 3. Fontanería y sanitarios | C17: Redes completas de fontanería/desagües baño y cocina, plato ducha resina con mampara, inodoro y mueble 80 cm | D17: =Desglose!F21
B18: 4. Electricidad | C18: Cuadro eléctrico general nuevo y 12 puntos eléctricos nuevos en cocina según normativa | D18: =Desglose!F24
B19: 5. Carpintería y mobiliario | C19: Suelo laminado roble AC5 S01 en 55 m², rodapié blanco, 4 puertas lacadas, cocina 5 ml verde salvia, península y encimeras cuarzo 7 ml | D19: =Desglose!F31
B20: 6. Pintura | C20: Pintura plástica lisa blanco roto P03 en 210 m² de techos y paredes de toda la vivienda | D20: =Desglose!F33
C21: BASE IMPONIBLE: | D21: =SUM(D15:D20)
C22: IVA (10 % reforma de vivienda): | D22: =D21*0.10
C23: TOTAL PRESUPUESTO CON IVA: | D23: =D21+D22
B25: Forma de Pago:
B26: • 40 % al inicio de los trabajos: | D26: =D23*0.40
B27: • 40 % a mitad de obra: | D27: =D23*0.40
B28: • 20 % a la finalización y entrega: | D28: =D23*0.20
B30: Comparativa con Presupuesto Mental del Cliente:
B31: Presupuesto estimado por Lucía y Andrés: | D31: 35000
B32: Propuesta Alféizar Reformas (IVA incl.): | D32: =D23
B33: Margen favorable para los clientes: | D33: =D31-D23

Sheet Desglose
A1: ALFÉIZAR REFORMAS · PRESUPUESTO POR INDUSTRIALES (OFICIOS)
A2: Proyecto: 01-Piso García | Clientes: Lucía y Andrés García | Ubicación: Ruzafa, Valencia (60 m²)
A4: Capítulo (Industrial) | B4: Partida / Descripción con Suministro y Colocación | C4: Ud. | D4: Medición | E4: Precio (€) | F4: Importe (€) | G4: Proveedor / Material
A5: 1. Derribos y gestión de residuos | B5: Demolición manual de tabique divisorio de ladrillo entre cocina y salón (4,00 m x 2,60 m) | C5: m² | D5: 10.4 | E5: 18 | F5: =D5*E5 | G5: -
A6: 1. Derribos y gestión de residuos | B6: Levantado de pavimento existente en toda la vivienda (excepto baño) y limpieza de base | C6: m² | D6: 55 | E6: 12 | F6: =D6*E6 | G6: -
A7: 1. Derribos y gestión de residuos | B7: Picado y retirada de alicatado cerámico en paredes de baño hasta soporte base (9 m x 2,60 m) | C7: m² | D7: 23.4 | E7: 14 | F7: =D7*E7 | G7: -
A8: 1. Derribos y gestión de residuos | B8: Desmontaje y retirada completa de mobiliario de cocina actual, bancada y fregadero | C8: ud | D8: 1 | E8: 180 | F8: =D8*E8 | G8: -
A9: 1. Derribos y gestión de residuos | B9: Desconexión y retirada de sanitarios antiguos (bañera, inodoro y lavabo) | C9: ud | D9: 3 | E9: 45 | F9: =D9*E9 | G9: -
A10: 1. Derribos y gestión de residuos | B10: Contenedor para escombros a pie de calle, transporte y tasas en planta autorizada de residuos | C10: PA | D10: 1 | E10: 320 | F10: =D10*E10 | G10: -
A11: Subtotal 1. Derribos y gestión de residuos | F11: =SUM(F5:F10)
A12: 2. Albañilería y revestimientos cerámicos | B12: Suministro y colocación de cargadero metálico estructural en apertura de hueco cocina-salón (4 m) | C12: ud | D12: 1 | E12: 650 | F12: =D12*E12 | G12: -
A13: 2. Albañilería y revestimientos cerámicos | B13: Suministro y colocación de azulejo blanco mate 30x60 cm de Cerámicas Onda (modelo P01) en paredes de baño | C13: m² | D13: 23.4 | E13: 58 | F13: =D13*E13 | G13: Cerámicas Onda (2 sem)
A14: 2. Albañilería y revestimientos cerámicos | B14: Suministro y colocación de suelo porcelánico gris perla 60x60 cm de Cerámicas Onda (modelo S02) en baño | C14: m² | D14: 5 | E14: 63 | F14: =D14*E14 | G14: Cerámicas Onda (2 sem)
A15: Subtotal 2. Albañilería y revestimientos cerámicos | F15: =SUM(F12:F14)
A16: 3. Fontanería y aparatos sanitarios | B16: Instalación completa de fontanería y desagües de baño para ducha, inodoro y lavabo | C16: PA | D16: 1 | E16: 980 | F16: =D16*E16 | G16: -
A17: 3. Fontanería y aparatos sanitarios | B17: Instalación de fontanería y tomas de desagüe en cocina (fregadero, lavavajillas, lavadora) | C17: PA | D17: 1 | E17: 640 | F17: =D17*E17 | G17: -
A18: 3. Fontanería y aparatos sanitarios | B18: Suministro e instalación de plato de ducha de resina antideslizante con mampara de vidrio templado (B01) | C18: ud | D18: 1 | E18: 890 | F18: =D18*E18 | G18: -
A19: 3. Fontanería y aparatos sanitarios | B19: Suministro e instalación de inodoro compacto adosado a pared de porcelana blanca con tapa amortiguada (B02) | C19: ud | D19: 1 | E19: 310 | F19: =D19*E19 | G19: -
A20: 3. Fontanería y aparatos sanitarios | B20: Suministro e instalación de mueble suspendido de lavabo 80 cm con espejo a juego y grifería monomando (B03) | C20: ud | D20: 1 | E20: 460 | F20: =D20*E20 | G20: -
A21: Subtotal 3. Fontanería y aparatos sanitarios | F21: =SUM(F16:F20)
A22: 4. Electricidad | B22: Suministro e instalación de cuadro eléctrico general nuevo según normativa REBT (I02) | C22: ud | D22: 1 | E22: 520 | F22: =D22*E22 | G22: -
A23: 4. Electricidad | B23: Suministro e instalación de puntos eléctricos nuevos en cocina para electrodomésticos y tomas de corriente (I01) | C23: ud | D23: 12 | E23: 48 | F23: =D23*E23 | G23: -
A24: Subtotal 4. Electricidad | F24: =SUM(F22:F23)
A25: 5. Carpintería y mobiliario | B25: Suministro y colocación de suelo laminado roble natural AC5 de Maderas Turia (modelo S01) sobre aislante | C25: m² | D25: 55 | E25: 38 | F25: =D25*E25 | G25: Maderas Turia (1 sem)
A26: 5. Carpintería y mobiliario | B26: Suministro y colocación de rodapié lacado en blanco de 8 cm fijado a pared y sellado (R05) | C26: ml | D26: 54 | E26: 8 | F26: =D26*E26 | G26: -
A27: 5. Carpintería y mobiliario | B27: Suministro y colocación de puertas interiores de paso abatibles lacadas en blanco con tapajuntas y manivelas (C01) | C27: ud | D27: 4 | E27: 340 | F27: =D27*E27 | G27: -
A28: 5. Carpintería y mobiliario | B28: Suministro y montaje de mobiliario de cocina en L (5 ml) con frentes verde salvia (modelo M02) y cierre amortiguado (K01) | C28: ml | D28: 5 | E28: 620 | F28: =D28*E28 | G28: Frentes M02 verde salvia
A29: 5. Carpintería y mobiliario | B29: Suministro y montaje de península divisoria cocina-salón (2 ml) con estructura y muebles bajos a dos caras (K02) | C29: ud | D29: 1 | E29: 1450 | F29: =D29*E29 | G29: Frentes M02 verde salvia
A30: 5. Carpintería y mobiliario | B30: Suministro e instalación de encimera de cuarzo blanco 2 cm de Encimeras Levante (modelo E01) en bancada y península | C30: ml | D30: 7 | E30: 270 | F30: =D30*E30 | G30: Encimeras Levante (3 sem)
A31: Subtotal 5. Carpintería y mobiliario | F31: =SUM(F25:F30)
A32: 6. Pintura | B32: Suministro y aplicación de pintura plástica lisa color blanco roto (acabado P03) en paredes y techos excepto baño (R04) | C32: m² | D32: 210 | E32: 9 | F32: =D32*E32 | G32: P03 blanco roto incluida
A33: Subtotal 6. Pintura | F33: =SUM(F32:F32)
E35: BASE IMPONIBLE: | F35: =F11+F15+F21+F24+F31+F33
E36: IVA (10%): | F36: =F35*0.10
E37: TOTAL PRESUPUESTO: | F37: =F35+F36
